llm_nexus/__init__.py
llm_nexus/model_provider.py
llm_nexus/_logging/__init__.py
llm_nexus/_logging/log.py
llm_nexus/_utils/__init__.py
llm_nexus/_utils/completions.py
llm_nexus/_utils/function_calls.py
llm_nexus/providers/__init__.py
llm_nexus/providers/_anthropic_provider.py
llm_nexus/providers/_googleai_provider.py
llm_nexus/providers/_model_interface.py
llm_nexus/providers/_openai_provider.py
llm_nexus-0.2.0.dist-info/LICENSE
llm_nexus-0.2.0.dist-info/METADATA
llm_nexus-0.2.0.dist-info/WHEEL
llm_nexus-0.2.0.dist-info/top_level.txt
llm_nexus-0.2.0.dist-info/RECORD
