Metadata-Version: 2.1
Name: llm_nexus
Version: 0.2.0
Summary: A unified interface for multiple language model providers
Home-page: https://github.com/dtedesco1/llm_nexus
Author: Daniel Tedesco
Author-email: Daniel Tedesco <dtedesco1@gmail.com>
License: MIT
Project-URL: Homepage, https://github.com/dtedesco1/llm_nexus
Project-URL: Repository, https://github.com/dtedesco1/llm_nexus.git
Classifier: Development Status :: 4 - Beta
Classifier: Intended Audience :: Developers
Classifier: License :: OSI Approved :: MIT License
Classifier: Programming Language :: Python :: 3
Classifier: Programming Language :: Python :: 3.8
Classifier: Programming Language :: Python :: 3.9
Classifier: Programming Language :: Python :: 3.10
Classifier: Programming Language :: Python :: 3.11
Classifier: Programming Language :: Python :: 3.12
Requires-Python: >=3.7
License-File: LICENSE
Requires-Dist: openai>=1.0.0
Requires-Dist: anthropic>=0.7.0
Requires-Dist: google-generativeai>=0.3.0
